setup.py
cat/__init__.py
cat/cli/__init__.py
cat/cli/cat.py
cat/cli/operators/__init__.py
cat/pages/__init__.py
cat/pages/hello.py
cat/server/__init__.py
cat/server/blog.py
cat/server/config.py
catg.egg-info/PKG-INFO
catg.egg-info/SOURCES.txt
catg.egg-info/dependency_links.txt
catg.egg-info/entry_points.txt
catg.egg-info/not-zip-safe
catg.egg-info/requires.txt
catg.egg-info/top_level.txt